apininja.py
apininja-0.1.9.dist-info/METADATA
apininja-0.1.9.dist-info/WHEEL
apininja-0.1.9.dist-info/entry_points.txt
apininja-0.1.9.dist-info/top_level.txt
apininja-0.1.9.dist-info/RECORD
